Assignment2/main_src.vhd
library IEEE;

use IEEE.STD_LOGIC_1164.ALL;

entity main_src is 

    port ( x : in STD_LOGIC;
           f : out STD_LOGIC);      
end main_src;

architecture Behavioral of main_src is

    begin

        f <= x;

end Behavioral;

Assignment2/main_tb.vhd
LIBRARY ieee;
USE ieee.std_logic_1164.ALL;

ENTITY main_tb IS 
END main_tb;

ARCHITECTURE behaivor OF main_tb IS

    COMPONENT main_src 
    PORT(
        x : IN STD_LOGIC;
        f : OUT STD_LOGIC
        );   
    END COMPONENT;

    signal x : std_logic := '0';
    signal f : std_logic;


BEGIN

    utt: main_src PORT MAP (
        x => x,
        f => f
    );

    stim_proc: process
    begin
    wait for 1 ns;
    x <= not x;
    end process;

END;

Assignment2/main.vcd
$date
  Sat Feb 12 19:00:33 2022
$end
$version
  GHDL v0
$end
$timescale
  1 fs
$end
$scope module standard $end
$upscope $end
$scope module std_logic_1164 $end
$upscope $end
$scope module main_tb $end
$var reg 1 ! x $end
$var reg 1 " f $end
$scope module utt $end
$var reg 1 # x $end
$var reg 1 $ f $end
$upscope $end
$upscope $end
$enddefinitions $end
#0
0!
0"
0#
0$
#1000000
1!
1"
1#
1$
#2000000
0!
0"
0#
0$
#3000000
1!
1"
1#
1$
#4000000
0!
0"
0#
0$
#5000000
1!
1"
1#
1$
#6000000
0!
0"
0#
0$
#7000000
1!
1"
1#
1$
#8000000
0!
0"
0#
0$
#9000000
1!
1"
1#
1$
#10000000
0!
0"
0#
0$
#11000000
1!
1"
1#
1$
#12000000
0!
0"
0#
0$
#13000000
1!
1"
1#
1$
